LICENSE
MANIFEST.in
README.md
setup.cfg
setup.py
autooc/__init__.py
autooc/autooc.py
autooc.egg-info/PKG-INFO
autooc.egg-info/SOURCES.txt
autooc.egg-info/dependency_links.txt
autooc.egg-info/requires.txt
autooc.egg-info/top_level.txt
autooc/algorithm/__init__.py
autooc/algorithm/hill_climbing.py
autooc/algorithm/mapper.py
autooc/algorithm/parameters.py
autooc/algorithm/search_loop.py
autooc/algorithm/step.py
autooc/algorithm/distributed_algorithm/__init__.py
autooc/algorithm/distributed_algorithm/search_loop.py
autooc/algorithm/distributed_algorithm/step.py
autooc/fitness/__init__.py
autooc/fitness/bic.py
autooc/fitness/evaluation.py
autooc/fitness/minimise_nodes.py
autooc/fitness/num_params.py
autooc/fitness/predict_time.py
autooc/fitness/progsys.py
autooc/fitness/pymax.py
autooc/fitness/sequence_match.py
autooc/fitness/string_match.py
autooc/fitness/training_time.py
autooc/fitness/base_ff_classes/__init__.py
autooc/fitness/base_ff_classes/base_ff.py
autooc/fitness/base_ff_classes/ff_template.py
autooc/fitness/base_ff_classes/moo_ff.py
autooc/fitness/multi_objective/__init__.py
autooc/fitness/multi_objective/binary_phenotype_to_float.py
autooc/fitness/multi_objective/singlefit_autoencoders.py
autooc/fitness/multi_objective/singlefit_multiobj.py
autooc/fitness/multi_objective/zdt1.py
autooc/fitness/supervised_learning/__init__.py
autooc/fitness/supervised_learning/boolean_problem.py
autooc/fitness/supervised_learning/classification.py
autooc/fitness/supervised_learning/if_else_classifier.py
autooc/fitness/supervised_learning/regression.py
autooc/fitness/supervised_learning/regression_random_polynomial.py
autooc/fitness/supervised_learning/supervised_learning.py
autooc/fitness/supervised_learning/supervised_learning_backup.py
autooc/grammars/autoencoders.bnf
autooc/grammars/autoencoders.pybnf
autooc/grammars/autoencoders_v2.pybnf
autooc/grammars/autoencoders_v3.pybnf
autooc/grammars/autoencoders_v4.pybnf
autooc/grammars/iforest.pybnf
autooc/grammars/lof.pybnf
autooc/grammars/multi_algo.pybnf
autooc/grammars/nas.pybnf
autooc/grammars/svm.pybnf
autooc/grammars/vae.pybnf
autooc/operators/__init__.py
