Metadata-Version: 2.1
Name: autooc
Version: 0.0.13.3
Summary: AutoOC: Automated Machine Learning (AutoML) library for One-Class Learning
Home-page: https://github.com/luisferreira97/AutoOC
Author: Luís Ferreira
Author-email: luis_ferreira223@hotmail.com
Keywords: automl,machine learning,one-class learning,one-class classification,autoencoder,isolation forest,one-class svm
Classifier: Programming Language :: Python :: 3
Classifier: License :: OSI Approved :: MIT License
Classifier: Operating System :: OS Independent
Requires-Python: >=3.6, <3.9
License-File: LICENSE
